encrypted_fields/__init__.py
encrypted_fields/fields.py
encrypted_fields/models.py
encrypted_fields/tests.py
django_encrypted_fields_2-1.1.13.dist-info/LICENCE.txt
django_encrypted_fields_2-1.1.13.dist-info/METADATA
django_encrypted_fields_2-1.1.13.dist-info/WHEEL
django_encrypted_fields_2-1.1.13.dist-info/top_level.txt
django_encrypted_fields_2-1.1.13.dist-info/RECORD
